<?xml version="1.0" encoding="ISO-8859-1"?>
<message_catalog package_key="xowf" locale="en_US" charset="ISO-8859-1">

  <msg key="Exercise">Exercise</msg>
  <msg key="Grading-Scheme">Grading Scheme</msg>
  <msg key="Grading-Score">Score</msg>
  <msg key="Shuffle">Shuffle</msg>
  <msg key="Days">Days</msg>
  <msg key="Day">Day</msg>
  <msg key="Minutes">Minutes</msg>
  <msg key="Minute">Minute</msg>
  <msg key="Hours">Hours</msg>
  <msg key="Hour">Hour</msg>
  <msg key="Seconds">Seconds</msg>
  <msg key="Second">Second</msg>
  <msg key="remaining">remaining</msg>
  <msg key="alternative">Alternative</msg>
  <msg key="answer_correct">That is correct!</msg>
  <msg key="answer_incorrect">Sorry, incorrect!</msg>
  <msg key="columns">Columns</msg>
  <msg key="correct">Correct?</msg>
  <msg key="exercise-text">Exercise Text</msg>
  <msg key="exercise_mc">Multiple Choice Exercise</msg>
  <msg key="exercise_ot">Open Text Exercise</msg>
  <msg key="exercise_sc">Single Choice Exercise</msg>
  <msg key="feedback">Feedback</msg>
  <msg key="feedback_correct">Feedback Correct</msg>
  <msg key="feedback_incorrect">Feedback Incorrect</msg>
  <msg key="lines">Lines</msg>
  <msg key="menu-New-Extra-Workflow">New Workflow</msg>
  <msg key="answer">Answer</msg>
  <msg key="answers">Answers</msg>
  <msg key="submitted_answers">Submitted Answers</msg>
  <msg key="answer_lines">Answer Lines</msg>
  <msg key="answer_columns">Answer Columns</msg>
  <msg key="correct_when">Correct When</msg>
  <msg key="online-exam-draft_exam">Draft Exam (not published)</msg>
  <msg key="online-exam-open">Exam open (published)</msg>
  <msg key="online-exam-closed">Exam closed</msg>
  <msg key="answer">Answer</msg>
  <msg key="question">Question</msg>
  <msg key="questions">Questions</msg>
  <msg key="first_question">First Question</msg>
  <msg key="next_question">Next Question</msg>
  <msg key="previous_question">Previous Question</msg>
  <msg key="restart">Restart</msg>
  <msg key="refresh">Refresh</msg>
  <msg key="print">Print</msg>
  <msg key="testrun">Testrun</msg>
  <msg key="please_answer">Please answer</msg>
  <msg key="participant">Participant</msg>
  <msg key="participants_answered_question">participants answered this question</msg>
  <msg key="results">Results</msg>
  <msg key="show_results">Show Results</msg>
  <msg key="results_of">Results of</msg>

  <msg key="online-exam-actual_signature">Actual Signature</msg>
  <msg key="online-exam-submission_signature">Submission Signature</msg>

  <msg key="Signature">Signature</msg>
  <msg key="Signature_help_text">Provide a digital finger print of submitted answers as proof of submitted content</msg>

  <msg key="online-exam-select">Create Exam</msg>
  <msg key="online-exam-review">Review Exam</msg>
  <msg key="sc_question">Single Choice Question</msg>
  <msg key="mc_question">Multiple Choice Question</msg>
  <msg key="text_question">Text Question</msg>
  <msg key="ul_question">File Upload Question</msg>
  <msg key="sub_question">Sub-Question</msg>
  <msg key="reorder_question">Ordering Question</msg>
  <msg key="reorder_question_elements">Ordering Elements</msg>

  <msg key="show_max">Show Max</msg>

  <msg key="shuffle_none">None</msg>
  <msg key="shuffle_peruser">Per user</msg>
  <msg key="shuffle_always">Always</msg>

  <msg key="menu-New-Item-TextInteraction">Text Interaction</msg>
  <msg key="menu-New-Item-ShortTextInteraction">Short Text Interaction</msg>
  <msg key="menu-New-Item-MCInteraction">MC Interaction</msg>
  <msg key="menu-New-Item-SCInteraction">SC Interaction</msg>
  <msg key="menu-New-Item-UploadInteraction">Upload Interaction</msg>
  <msg key="menu-New-Item-ReorderInteraction">Ordering Interaction</msg>

  <msg key="menu-New-App-OnlineExam">Online Exam</msg>
  <msg key="menu-New-App-InclassQuiz">Inclass Quiz</msg>
  <msg key="menu-New-App-InclassExam">Inclass Exam</msg>

  <msg key="inclass-exam-draft_exam">Draft Inclass Exam (not published)</msg>
  <msg key="inclass-exam-open">Inclass Exam open (published)</msg>
  <msg key="inclass-exam-closed">Inclass Exam closed</msg>
  <msg key="inclass-exam-review">Inclass Exam closed (review open)</msg>
  <msg key="Exam-review-not-open">Exam review for this exam is not open</msg>

  <msg key="Created_Questions">Created Questions</msg>
  <msg key="Created_Assessments">Created Assessments</msg>
  <msg key="nr_changes">Number of changes</msg>
  <msg key="Duration">Duration</msg>
  <msg key="not_submitted">not submitted</msg>
  <msg key="submitted">submitted</msg>
  <msg key="Status">State</msg>
  <msg key="Make_live_revision">Use displayed revision as submission</msg>
  <msg key="Goto_this_revision">Go to this revision</msg>
  <msg key="Displayed_revision">Displayed revision</msg>
  <msg key="Live_revision">Submission revision</msg>
  <msg key="Solution">Solution</msg>
  <msg key="Proctoring">Proctoring</msg>
  <msg key="Proctoring_help_text">Use E-Proctoring for this exam</msg>
  <msg key="Synchronized">Synchronized Exam</msg>
  <msg key="Synchronized_help_text">Is the exam duration strictly controlled by the lecturer, or does every student get his working time displayed, independent from his starting time.</msg>
  <msg key="Exam_published">Exam Published</msg>
  <msg key="since_published">since published</msg>
  <msg key="Achieved_points">Achieved Points</msg>
</message_catalog>
